<?xml version="1.0" encoding="UTF-8" standalone="yes"?>
<mappings xmlns="http://dozer.sourceforge.net" xmlns:xsi="http://www.w3.org/2001/XMLSchema-instance" xsi:schemaLocation="http://dozer.sourceforge.net http://dozer.sourceforge.net/schema/beanmapping.xsd">
    <configuration>
        <wildcard>false</wildcard>
    </configuration>
    <mapping>
        <class-a>bpmsuiteresponse.ProcessInstanceResponse</class-a>
        <class-b>org.blogdemo.endpoint.BPMSuiteResponse</class-b>
        <field>
            <a>id</a>
            <b>id</b>
        </field>
        <field>
            <a>processId</a>
            <b>processId</b>
        </field>
        <field>
            <a>state</a>
            <b>state</b>
        </field>
        <field>
            <a>status</a>
            <b>status</b>
        </field>
    </mapping>
</mappings>
